hole/__init__.py
hole/exceptions.py
hole-0.7.0.dist-info/LICENSE
hole-0.7.0.dist-info/METADATA
hole-0.7.0.dist-info/WHEEL
hole-0.7.0.dist-info/top_level.txt
hole-0.7.0.dist-info/zip-safe
hole-0.7.0.dist-info/RECORD
