Metadata-Version: 2.1
Name: hole
Version: 0.7.0
Summary: Python API for interacting with *hole.
Home-page: https://github.com/home-assistant-ecosystem/python-hole
Author: Fabian Affolter
Author-email: fabian@affolter-engineering.ch
License: MIT
Download-URL: https://github.com/home-assistant-ecosystem/python-hole/releases
Platform: UNKNOWN
Classifier: Development Status :: 3 - Alpha
Classifier: Environment :: Console
Classifier: Intended Audience :: Developers
Classifier: License :: OSI Approved :: MIT License
Classifier: Operating System :: MacOS :: MacOS X
Classifier: Operating System :: Microsoft :: Windows
Classifier: Operating System :: POSIX
Classifier: Programming Language :: Python :: 3.8
Classifier: Programming Language :: Python :: 3.9
Classifier: Topic :: Utilities
Requires-Python: >=3.8
License-File: LICENSE
Requires-Dist: aiohttp (<4)
Requires-Dist: async-timeout (<5,>4)
